jupyter_module_loader/__init__.py
notebook_finder/__init__.py
jupyter_module_loader-0.0.1.dist-info/LICENSE
jupyter_module_loader-0.0.1.dist-info/METADATA
jupyter_module_loader-0.0.1.dist-info/WHEEL
jupyter_module_loader-0.0.1.dist-info/top_level.txt
jupyter_module_loader-0.0.1.dist-info/RECORD
