Metadata-Version: 2.1
Name: jupyter-module-loader
Version: 0.0.1
Summary: A python package that allows importing Jupyter notebooks as python modules
Home-page: https://github.com/pitamar/jupyter-module-loader
Author: Itamar Schen
Author-email: itamarschen@gmail.com
License: UNKNOWN
Platform: UNKNOWN
Classifier: Programming Language :: Python :: 3
Classifier: License :: OSI Approved :: Apache Software License
Classifier: Operating System :: OS Independent
Requires-Python: >=3.6
